ovos_skill_personal/LICENSE
ovos_skill_personal/MANIFEST.in
ovos_skill_personal/README.md
ovos_skill_personal/__init__.py
ovos_skill_personal/requirements.txt
ovos_skill_personal/settingsmeta.json
ovos_skill_personal/version.py
ovos_skill_personal/locale/ca-es/WhatAreYou.intent
ovos_skill_personal/locale/ca-es/WhenWereYouBorn.intent
ovos_skill_personal/locale/ca-es/WhereWereYouBorn.intent
ovos_skill_personal/locale/ca-es/WhoAreYou.intent
ovos_skill_personal/locale/ca-es/WhoMadeYou.intent
ovos_skill_personal/locale/ca-es/skill.json
ovos_skill_personal/locale/ca-es/what.am.i.dialog
ovos_skill_personal/locale/ca-es/when.was.i.born.dialog
ovos_skill_personal/locale/ca-es/where.was.i.born.dialog
ovos_skill_personal/locale/ca-es/who.am.i.dialog
ovos_skill_personal/locale/ca-es/who.made.me.dialog
ovos_skill_personal/locale/da-dk/WhatAreYou.intent
ovos_skill_personal/locale/da-dk/WhenWereYouBorn.intent
ovos_skill_personal/locale/da-dk/WhereWereYouBorn.intent
ovos_skill_personal/locale/da-dk/WhoAreYou.intent
ovos_skill_personal/locale/da-dk/WhoMadeYou.intent
ovos_skill_personal/locale/da-dk/skill.json
ovos_skill_personal/locale/da-dk/what.am.i.dialog
ovos_skill_personal/locale/da-dk/when.was.i.born.dialog
ovos_skill_personal/locale/da-dk/where.was.i.born.dialog
ovos_skill_personal/locale/da-dk/who.am.i.dialog
ovos_skill_personal/locale/da-dk/who.made.me.dialog
ovos_skill_personal/locale/de-de/WhatAreYou.intent
ovos_skill_personal/locale/de-de/WhenWereYouBorn.intent
ovos_skill_personal/locale/de-de/WhereWereYouBorn.intent
ovos_skill_personal/locale/de-de/WhoAreYou.intent
ovos_skill_personal/locale/de-de/WhoMadeYou.intent
ovos_skill_personal/locale/de-de/skill.json
ovos_skill_personal/locale/de-de/what.am.i.dialog
ovos_skill_personal/locale/de-de/when.was.i.born.dialog
ovos_skill_personal/locale/de-de/where.was.i.born.dialog
ovos_skill_personal/locale/de-de/who.am.i.dialog
ovos_skill_personal/locale/de-de/who.made.me.dialog
ovos_skill_personal/locale/en-us/WhatAreYou.intent
ovos_skill_personal/ovos_skill_personal.egg-info/PKG-INFO
ovos_skill_personal/ovos_skill_personal.egg-info/SOURCES.txt
ovos_skill_personal/ovos_skill_personal.egg-info/dependency_links.txt
ovos_skill_personal/ovos_skill_personal.egg-info/entry_points.txt
ovos_skill_personal/ovos_skill_personal.egg-info/requires.txt
ovos_skill_personal/ovos_skill_personal.egg-info/top_level.txt
ovos_skill_personal-0.1.19.dist-info/LICENSE
ovos_skill_personal-0.1.19.dist-info/METADATA
ovos_skill_personal-0.1.19.dist-info/WHEEL
ovos_skill_personal-0.1.19.dist-info/entry_points.txt
ovos_skill_personal-0.1.19.dist-info/top_level.txt
ovos_skill_personal-0.1.19.dist-info/RECORD
