Metadata-Version: 2.1
Name: ovos-skill-personal
Version: 0.1.19
Summary: OVOS personal skill plugin
Home-page: https://github.com/OpenVoiceOS/ovos-skill-personal
Author: JarbasAi
Author-email: jarbasai@mailfence.com
License: Apache-2.0
Keywords: ovos skill plugin
License-File: LICENSE
Requires-Dist: ovos-utils>=0.0.38
Requires-Dist: ovos-workshop<8.0.0,>=0.0.15
